function_limiter/__init__.py
function_limiter/_version.py
function_limiter/limiter.py
Function_Limiter-0.2.0.dist-info/LICENSE
Function_Limiter-0.2.0.dist-info/METADATA
Function_Limiter-0.2.0.dist-info/WHEEL
Function_Limiter-0.2.0.dist-info/top_level.txt
Function_Limiter-0.2.0.dist-info/RECORD
